{"v":"5.12.1","fr":60,"ip":0,"op":90,"w":430,"h":430,"nm":"wired-outline-2613-calendar-subscription","ddd":0,"assets":[{"id":"comp_1","nm":"hover-click","fr":60,"layers":[{"ddd":0,"ind":1,"ty":4,"nm":"Ellipse 6","parent":2,"sr":1,"ks":{"o":{"a":0,"k":100,"ix":11},"r":{"a":0,"k":0,"ix":10},"p":{"a":0,"k":[-0.04,0,0],"ix":2,"l":2},"a":{"a":0,"k":[-68.544,12.462,0],"ix":1,"l":2},"s":{"a":0,"k":[100,100,100],"ix":6,"l":2}},"ao":0,"shapes":[{"ty":"gr","it":[{"ind":0,"ty":"sh","ix":1,"ks":{"a":0,"k":{"i":[[0,0],[0,0],[0,0]],"o":[[0,0],[0,0],[0,0]],"v":[[-25.099,-12.55],[0,12.55],[25.099,-12.55]],"c":false},"ix":2},"nm":"Path 1","mn":"ADBE Vector Shape - Group","hd":false},{"ty":"st","c":{"a":0,"k":[0.8313725490196079,0.6862745098039216,0.21568627450980393,1],"ix":3,"x":"var $bm_rt;\n$bm_rt = comp('wired-outline-2613-calendar-subscription').layer('control').effect('secondary')('Color');"},"o":{"a":0,"k":100,"ix":4},"w":{"a":0,"k":18,"ix":5,"x":"var $bm_rt;\n$bm_rt = $bm_mul($bm_div(value, 3), comp('wired-outline-2613-calendar-subscription').layer('control').effect('stroke')('Menu'));"},"lc":2,"lj":2,"bm":0,"nm":".secondary","mn":"ADBE Vector Graphic - Stroke","hd":false,"cl":"secondary"},{"ty":"tr","p":{"a":0,"k":[0,0],"ix":2},"a":{"a":0,"k":[0,0],"ix":1},"s":{"a":0,"k":[100,100],"ix":3},"r":{"a":0,"k":0,"ix":6},"o":{"a":0,"k":100,"ix":7},"sk":{"a":0,"k":0,"ix":4},"sa":{"a":0,"k":0,"ix":5},"nm":"Transform"}],"nm":"Ellipse 5","np":2,"cix":2,"bm":0,"ix":1,"mn":"ADBE Vector Group","hd":false}],"ip":0,"op":1766,"st":-34,"ct":1,"bm":0},{"ddd":0,"ind":2,"ty":4,"nm":"Ellipse 5","sr":1,"ks":{"o":{"a":0,"k":100,"ix":11},"r":{"a":1,"k":[{"i":{"x":[0],"y":[1]},"o":{"x":[0.07],"y":[0]},"t":0,"s":[0]},{"t":90,"s":[360]}],"ix":10},"p":{"a":0,"k":[320,325,0],"ix":2,"l":2},"a":{"a":0,"k":[0,0,0],"ix":1,"l":2},"s":{"a":0,"k":[100,100,100],"ix":6,"l":2}},"ao":0,"shapes":[{"ty":"gr","it":[{"ind":0,"ty":"sh","ix":1,"ks":{"a":0,"k":{"i":[[0,0],[26.325,0],[0,38.66],[-38.66,0],[-1.756,-37.097]],"o":[[-11.953,21.479],[-38.66,0],[0,-38.66],[37.532,0],[0.053,1.115]],"v":[[61.209,33.989],[0,70],[-70,0],[0,-70],[69.921,-3.365]],"c":false},"ix":2},"nm":"Path 1","mn":"ADBE Vector Shape - Group","hd":false},{"ty":"tm","s":{"a":0,"k":0,"ix":1},"e":{"a":0,"k":100,"ix":2},"o":{"a":0,"k":0,"ix":3},"m":1,"ix":2,"nm":"Trim Paths 1","mn":"ADBE Vector Filter - Trim","hd":false},{"ty":"st","c":{"a":0,"k":[0.8313725490196079,0.6862745098039216,0.21568627450980393,1],"ix":3,"x":"var $bm_rt;\n$bm_rt = comp('wired-outline-2613-calendar-subscription').layer('control').effect('secondary')('Color');"},"o":{"a":0,"k":100,"ix":4},"w":{"a":0,"k":18,"ix":5,"x":"var $bm_rt;\n$bm_rt = $bm_mul($bm_div(value, 3), comp('wired-outline-2613-calendar-subscription').layer('control').effect('stroke')('Menu'));"},"lc":2,"lj":2,"bm":0,"nm":".secondary","mn":"ADBE Vector Graphic - Stroke","hd":false,"cl":"secondary"},{"ty":"tr","p":{"a":0,"k":[0,0],"ix":2},"a":{"a":0,"k":[0,0],"ix":1},"s":{"a":0,"k":[100,100],"ix":3},"r":{"a":0,"k":0,"ix":6},"o":{"a":0,"k":100,"ix":7},"sk":{"a":0,"k":0,"ix":4},"sa":{"a":0,"k":0,"ix":5},"nm":"Transform"}],"nm":"Ellipse 5","np":3,"cix":2,"bm":0,"ix":1,"mn":"ADBE Vector Group","hd":false}],"ip":0,"op":1766,"st":-34,"ct":1,"bm":0},{"ddd":0,"ind":3,"ty":4,"nm":"fill","parent":4,"sr":1,"ks":{"o":{"a":0,"k":100,"ix":11},"r":{"a":0,"k":0,"ix":10},"p":{"a":0,"k":[250,292.826,0],"ix":2,"l":2},"a":{"a":0,"k":[250,292.826,0],"ix":1,"l":2},"s":{"a":0,"k":[100,100,100],"ix":6,"l":2}},"ao":0,"shapes":[{"ty":"gr","it":[{"ind":0,"ty":"sh","ix":1,"ks":{"a":0,"k":{"i":[[0,0],[0,0],[0,0],[0,0]],"o":[[0,0],[0,0],[0,0],[0,0]],"v":[[161,118.335],[-161,118.335],[-161,-118.335],[161,-118.335]],"c":true},"ix":2},"nm":"Path 1","mn":"ADBE Vector Shape - Group","hd":false},{"ty":"tm","s":{"a":1,"k":[{"i":{"x":[0.667],"y":[1]},"o":{"x":[0.333],"y":[0]},"t":0,"s":[9.7]},{"i":{"x":[0.667],"y":[1]},"o":{"x":[0.333],"y":[0]},"t":8,"s":[8.7]},{"i":{"x":[0.667],"y":[1]},"o":{"x":[0.333],"y":[0]},"t":18,"s":[9.7]},{"t":31,"s":[9.7]}],"ix":1},"e":{"a":1,"k":[{"i":{"x":[0.667],"y":[1]},"o":{"x":[0.333],"y":[0]},"t":0,"s":[91.6]},{"i":{"x":[0.667],"y":[1]},"o":{"x":[0.333],"y":[0]},"t":8,"s":[90.6]},{"i":{"x":[0.667],"y":[1]},"o":{"x":[0.333],"y":[0]},"t":18,"s":[91.6]},{"t":31,"s":[91.6]}],"ix":2},"o":{"a":0,"k":0,"ix":3},"m":1,"ix":2,"nm":"Trim Paths 1","mn":"ADBE Vector Filter - Trim","hd":false},{"ty":"st","c":{"a":0,"k":[0.8313725490196079,0.6862745098039216,0.21568627450980393,1],"ix":3,"x":"var $bm_rt;\n$bm_rt = comp('wired-outline-2613-calendar-subscription').layer('control').effect('primary')('Color');"},"o":{"a":0,"k":100,"ix":4},"w":{"a":0,"k":18,"ix":5,"x":"var $bm_rt;\n$bm_rt = $bm_mul($bm_div(value, 3), comp('wired-outline-2613-calendar-subscription').layer('control').effect('stroke')('Menu'));"},"lc":2,"lj":2,"bm":0,"nm":".primary","mn":"ADBE Vector Graphic - Stroke","hd":false,"cl":"primary"},{"ty":"tr","p":{"a":0,"k":[250,292.826],"ix":2},"a":{"a":0,"k":[0,0],"ix":1},"s":{"a":0,"k":[100,100],"ix":3},"r":{"a":0,"k":0,"ix":6},"o":{"a":0,"k":100,"ix":7},"sk":{"a":0,"k":0,"ix":4},"sa":{"a":0,"k":0,"ix":5},"nm":"Transform"}],"nm":"Group 1","np":3,"cix":2,"bm":0,"ix":1,"mn":"ADBE Vector Group","hd":false},{"ty":"gr","it":[{"d":1,"ty":"el","s":{"a":0,"k":[50,50],"ix":2},"p":{"a":0,"k":[0,0],"ix":3},"nm":"Ellipse Path 1","mn":"ADBE Vector Shape - Ellipse","hd":false},{"ty":"st","c":{"a":0,"k":[0.8313725490196079,0.6862745098039216,0.21568627450980393,1],"ix":3,"x":"var $bm_rt;\n$bm_rt = comp('wired-outline-2613-calendar-subscription').layer('control').effect('secondary')('Color');"},"o":{"a":0,"k":100,"ix":4},"w":{"a":0,"k":18,"ix":5,"x":"var $bm_rt;\n$bm_rt = $bm_mul($bm_div(value, 3), comp('wired-outline-2613-calendar-subscription').layer('control').effect('stroke')('Menu'));"},"lc":1,"lj":1,"ml":4,"bm":0,"nm":".secondary","mn":"ADBE Vector Graphic - Stroke","hd":false,"cl":"secondary"},{"ty":"tr","p":{"a":0,"k":[160.259,325.165],"ix":2},"a":{"a":0,"k":[0,0],"ix":1},"s":{"a":0,"k":[100,100],"ix":3},"r":{"a":0,"k":0,"ix":6},"o":{"a":0,"k":100,"ix":7},"sk":{"a":0,"k":0,"ix":4},"sa":{"a":0,"k":0,"ix":5},"nm":"Transform"}],"nm":"circle 5","np":2,"cix":2,"bm":0,"ix":2,"mn":"ADBE Vector Group","hd":false},{"ty":"gr","it":[{"d":1,"ty":"el","s":{"a":0,"k":[50,50],"ix":2},"p":{"a":0,"k":[0,0],"ix":3},"nm":"Ellipse Path 1","mn":"ADBE Vector Shape - Ellipse","hd":false},{"ty":"st","c":{"a":0,"k":[0.8313725490196079,0.6862745098039216,0.21568627450980393,1],"ix":3,"x":"var $bm_rt;\n$bm_rt = comp('wired-outline-2613-calendar-subscription').layer('control').effect('primary')('Color');"},"o":{"a":0,"k":100,"ix":4},"w":{"a":0,"k":18,"ix":5,"x":"var $bm_rt;\n$bm_rt = $bm_mul($bm_div(value, 3), comp('wired-outline-2613-calendar-subscription').layer('control').effect('stroke')('Menu'));"},"lc":1,"lj":1,"ml":4,"bm":0,"nm":".primary","mn":"ADBE Vector Graphic - Stroke","hd":false,"cl":"primary"},{"ty":"tr","p":{"a":0,"k":[250.157,325.165],"ix":2},"a":{"a":0,"k":[0,0],"ix":1},"s":{"a":0,"k":[100,100],"ix":3},"r":{"a":0,"k":0,"ix":6},"o":{"a":0,"k":100,"ix":7},"sk":{"a":0,"k":0,"ix":4},"sa":{"a":0,"k":0,"ix":5},"nm":"Transform"}],"nm":"circle 4","np":2,"cix":2,"bm":0,"ix":3,"mn":"ADBE Vector Group","hd":false},{"ty":"gr","it":[{"d":1,"ty":"el","s":{"a":0,"k":[50,50],"ix":2},"p":{"a":0,"k":[0,0],"ix":3},"nm":"Ellipse Path 1","mn":"ADBE Vector Shape - Ellipse","hd":false},{"ty":"st","c":{"a":0,"k":[0.8313725490196079,0.6862745098039216,0.21568627450980393,1],"ix":3,"x":"var $bm_rt;\n$bm_rt = comp('wired-outline-2613-calendar-subscription').layer('control').effect('primary')('Color');"},"o":{"a":0,"k":100,"ix":4},"w":{"a":0,"k":18,"ix":5,"x":"var $bm_rt;\n$bm_rt = $bm_mul($bm_div(value, 3), comp('wired-outline-2613-calendar-subscription').layer('control').effect('stroke')('Menu'));"},"lc":1,"lj":1,"ml":4,"bm":0,"nm":".primary","mn":"ADBE Vector Graphic - Stroke","hd":false,"cl":"primary"},{"ty":"tr","p":{"a":0,"k":[160.259,235.101],"ix":2},"a":{"a":0,"k":[0,0],"ix":1},"s":{"a":0,"k":[100,100],"ix":3},"r":{"a":0,"k":0,"ix":6},"o":{"a":0,"k":100,"ix":7},"sk":{"a":0,"k":0,"ix":4},"sa":{"a":0,"k":0,"ix":5},"nm":"Transform"}],"nm":"circle 3","np":2,"cix":2,"bm":0,"ix":4,"mn":"ADBE Vector Group","hd":false},{"ty":"gr","it":[{"d":1,"ty":"el","s":{"a":0,"k":[50,50],"ix":2},"p":{"a":0,"k":[0,0],"ix":3},"nm":"Ellipse Path 1","mn":"ADBE Vector Shape - Ellipse","hd":false},{"ty":"st","c":{"a":0,"k":[0.8313725490196079,0.6862745098039216,0.21568627450980393,1],"ix":3,"x":"var $bm_rt;\n$bm_rt = comp('wired-outline-2613-calendar-subscription').layer('control').effect('secondary')('Color');"},"o":{"a":0,"k":100,"ix":4},"w":{"a":0,"k":18,"ix":5,"x":"var $bm_rt;\n$bm_rt = $bm_mul($bm_div(value, 3), comp('wired-outline-2613-calendar-subscription').layer('control').effect('stroke')('Menu'));"},"lc":1,"lj":1,"ml":4,"bm":0,"nm":".secondary","mn":"ADBE Vector Graphic - Stroke","hd":false,"cl":"secondary"},{"ty":"tr","p":{"a":0,"k":[250.157,235.101],"ix":2},"a":{"a":0,"k":[0,0],"ix":1},"s":{"a":0,"k":[100,100],"ix":3},"r":{"a":0,"k":0,"ix":6},"o":{"a":0,"k":100,"ix":7},"sk":{"a":0,"k":0,"ix":4},"sa":{"a":0,"k":0,"ix":5},"nm":"Transform"}],"nm":"circle 2","np":2,"cix":2,"bm":0,"ix":5,"mn":"ADBE Vector Group","hd":false},{"ty":"gr","it":[{"d":1,"ty":"el","s":{"a":0,"k":[50,50],"ix":2},"p":{"a":0,"k":[0,0],"ix":3},"nm":"Ellipse Path 1","mn":"ADBE Vector Shape - Ellipse","hd":false},{"ty":"st","c":{"a":0,"k":[0.8313725490196079,0.6862745098039216,0.21568627450980393,1],"ix":3,"x":"var $bm_rt;\n$bm_rt = comp('wired-outline-2613-calendar-subscription').layer('control').effect('primary')('Color');"},"o":{"a":0,"k":100,"ix":4},"w":{"a":0,"k":18,"ix":5,"x":"var $bm_rt;\n$bm_rt = $bm_mul($bm_div(value, 3), comp('wired-outline-2613-calendar-subscription').layer('control').effect('stroke')('Menu'));"},"lc":1,"lj":1,"ml":4,"bm":0,"nm":".primary","mn":"ADBE Vector Graphic - Stroke","hd":false,"cl":"primary"},{"ty":"tr","p":{"a":0,"k":[340.032,235.101],"ix":2},"a":{"a":0,"k":[0,0],"ix":1},"s":{"a":0,"k":[100,100],"ix":3},"r":{"a":0,"k":0,"ix":6},"o":{"a":0,"k":100,"ix":7},"sk":{"a":0,"k":0,"ix":4},"sa":{"a":0,"k":0,"ix":5},"nm":"Transform"}],"nm":"circle","np":2,"cix":2,"bm":0,"ix":6,"mn":"ADBE Vector Group","hd":false}],"ip":0,"op":167.5,"st":0,"ct":1,"bm":0},{"ddd":0,"ind":4,"ty":4,"nm":"core 2","sr":1,"ks":{"o":{"a":0,"k":100,"ix":11},"r":{"a":0,"k":0,"ix":10},"p":{"a":1,"k":[{"i":{"x":0.667,"y":1},"o":{"x":0.333,"y":0},"t":0,"s":[216.424,115.184,0],"to":[0,0,0],"ti":[0,0,0]},{"i":{"x":0.667,"y":1},"o":{"x":0.333,"y":0},"t":8,"s":[216.424,125.184,0],"to":[0,0,0],"ti":[0,0,0]},{"i":{"x":0.667,"y":1},"o":{"x":0.333,"y":0},"t":18,"s":[216.424,112.184,0],"to":[0,0,0],"ti":[0,0,0]},{"t":31,"s":[216.424,115.184,0]}],"ix":2,"l":2},"a":{"a":0,"k":[251.424,150.184,0],"ix":1,"l":2},"s":{"a":0,"k":[100,100,100],"ix":6,"l":2}},"ao":0,"shapes":[{"ty":"gr","it":[{"ind":0,"ty":"sh","ix":1,"ks":{"a":0,"k":{"i":[[0,0],[0,0],[0,0],[0,0]],"o":[[0,0],[0,0],[0,0],[0,0]],"v":[[21.849,19.259],[-21.849,19.259],[-21.849,-19.259],[21.849,-19.259]],"c":true},"ix":2},"nm":"Path 1","mn":"ADBE Vector Shape - Group","hd":false},{"ty":"st","c":{"a":0,"k":[0.8313725490196079,0.6862745098039216,0.21568627450980393,1],"ix":3,"x":"var $bm_rt;\n$bm_rt = comp('wired-outline-2613-calendar-subscription').layer('control').effect('primary')('Color');"},"o":{"a":0,"k":100,"ix":4},"w":{"a":0,"k":18,"ix":5,"x":"var $bm_rt;\n$bm_rt = $bm_mul($bm_div(value, 3), comp('wired-outline-2613-calendar-subscription').layer('control').effect('stroke')('Menu'));"},"lc":2,"lj":2,"bm":0,"nm":".primary","mn":"ADBE Vector Graphic - Stroke","hd":false,"cl":"primary"},{"ty":"tr","p":{"a":0,"k":[356.952,108.098],"ix":2},"a":{"a":0,"k":[0,0],"ix":1},"s":{"a":0,"k":[100,100],"ix":3},"r":{"a":0,"k":0,"ix":6},"o":{"a":0,"k":100,"ix":7},"sk":{"a":0,"k":0,"ix":4},"sa":{"a":0,"k":0,"ix":5},"nm":"Transform"}],"nm":"Group 1","np":2,"cix":2,"bm":0,"ix":1,"mn":"ADBE Vector Group","hd":false},{"ty":"gr","it":[{"ind":0,"ty":"sh","ix":1,"ks":{"a":0,"k":{"i":[[0,0],[0,0],[0,0],[0,0]],"o":[[0,0],[0,0],[0,0],[0,0]],"v":[[21.849,19.259],[-21.849,19.259],[-21.849,-19.259],[21.849,-19.259]],"c":true},"ix":2},"nm":"Path 1","mn":"ADBE Vector Shape - Group","hd":false},{"ty":"st","c":{"a":0,"k":[0.8313725490196079,0.6862745098039216,0.21568627450980393,1],"ix":3,"x":"var $bm_rt;\n$bm_rt = comp('wired-outline-2613-calendar-subscription').layer('control').effect('primary')('Color');"},"o":{"a":0,"k":100,"ix":4},"w":{"a":0,"k":18,"ix":5,"x":"var $bm_rt;\n$bm_rt = $bm_mul($bm_div(value, 3), comp('wired-outline-2613-calendar-subscription').layer('control').effect('stroke')('Menu'));"},"lc":2,"lj":2,"bm":0,"nm":".primary","mn":"ADBE Vector Graphic - Stroke","hd":false,"cl":"primary"},{"ty":"tr","p":{"a":0,"k":[143.048,108.098],"ix":2},"a":{"a":0,"k":[0,0],"ix":1},"s":{"a":0,"k":[100,100],"ix":3},"r":{"a":0,"k":0,"ix":6},"o":{"a":0,"k":100,"ix":7},"sk":{"a":0,"k":0,"ix":4},"sa":{"a":0,"k":0,"ix":5},"nm":"Transform"}],"nm":"Group 2","np":2,"cix":2,"bm":0,"ix":2,"mn":"ADBE Vector Group","hd":false},{"ty":"gr","it":[{"ind":0,"ty":"sh","ix":1,"ks":{"a":0,"k":{"i":[[0,0],[0,0],[0,0],[0,0],[0,0]],"o":[[0,0],[0,0],[0,0],[0,0],[0,0]],"v":[[161,23.567],[-89.747,23.567],[-161,23.567],[-161,-23.567],[161,-23.567]],"c":true},"ix":2},"nm":"Path 1","mn":"ADBE Vector Shape - Group","hd":false},{"ty":"st","c":{"a":0,"k":[0.8313725490196079,0.6862745098039216,0.21568627450980393,1],"ix":3,"x":"var $bm_rt;\n$bm_rt = comp('wired-outline-2613-calendar-subscription').layer('control').effect('primary')('Color');"},"o":{"a":0,"k":100,"ix":4},"w":{"a":0,"k":18,"ix":5,"x":"var $bm_rt;\n$bm_rt = $bm_mul($bm_div(value, 3), comp('wired-outline-2613-calendar-subscription').layer('control').effect('stroke')('Menu'));"},"lc":2,"lj":2,"bm":0,"nm":".primary","mn":"ADBE Vector Graphic - Stroke","hd":false,"cl":"primary"},{"ty":"tr","p":{"a":0,"k":[250,150.924],"ix":2},"a":{"a":0,"k":[0,0],"ix":1},"s":{"a":0,"k":[100,100],"ix":3},"r":{"a":0,"k":0,"ix":6},"o":{"a":0,"k":100,"ix":7},"sk":{"a":0,"k":0,"ix":4},"sa":{"a":0,"k":0,"ix":5},"nm":"Transform"}],"nm":"Group 3","np":2,"cix":2,"bm":0,"ix":3,"mn":"ADBE Vector Group","hd":false}],"ip":0,"op":302.5,"st":2.5,"ct":1,"bm":0}]}],"layers":[{"ddd":0,"ind":1,"ty":3,"nm":"control","sr":1,"ks":{"o":{"a":0,"k":0,"ix":11},"r":{"a":0,"k":0,"ix":10},"p":{"a":0,"k":[0,0],"ix":2,"l":2},"a":{"a":0,"k":[0,0,0],"ix":1,"l":2},"s":{"a":0,"k":[100,100,100],"ix":6,"l":2}},"ao":0,"ef":[{"ty":5,"nm":"stroke","np":3,"mn":"Pseudo/@@qoQdGHXVRWiyg/Bn3+ni5Q","ix":1,"en":1,"ef":[{"ty":7,"nm":"Menu","mn":"Pseudo/@@qoQdGHXVRWiyg/Bn3+ni5Q-0001","ix":1,"v":{"a":0,"k":3,"ix":1}}]},{"ty":5,"nm":"primary","np":3,"mn":"ADBE Color Control","ix":2,"en":1,"ef":[{"ty":2,"nm":"Color","mn":"ADBE Color Control-0001","ix":1,"v":{"a":0,"k":[0.8313725490196079,0.6862745098039216,0.21568627450980393],"ix":1}}]},{"ty":5,"nm":"secondary","np":3,"mn":"ADBE Color Control","ix":3,"en":1,"ef":[{"ty":2,"nm":"Color","mn":"ADBE Color Control-0001","ix":1,"v":{"a":0,"k":[0.8313725490196079,0.6862745098039216,0.21568627450980393],"ix":1}}]}],"ip":0,"op":361,"st":0,"bm":0},{"ddd":0,"ind":3,"ty":0,"nm":"hover-click","refId":"comp_1","sr":1,"ks":{"o":{"a":0,"k":100,"ix":11},"r":{"a":0,"k":0,"ix":10},"p":{"a":0,"k":[215,215,0],"ix":2,"l":2},"a":{"a":0,"k":[215,215,0],"ix":1,"l":2},"s":{"a":0,"k":[100,100,100],"ix":6,"l":2}},"ao":0,"w":430,"h":430,"ip":0,"op":100,"st":0,"bm":0}],"markers":[{"tm":0,"cm":"default:hover-click","dr":90}],"props":{}}